estrutura_de_dados/__init__.py
estrutura_de_dados/fila.py
estrutura_de_dados/lista.py
estrutura_de_dados/pilha.py
estrutura_de_dados-0.0.1.dist-info/METADATA
estrutura_de_dados-0.0.1.dist-info/WHEEL
estrutura_de_dados-0.0.1.dist-info/top_level.txt
estrutura_de_dados-0.0.1.dist-info/RECORD
