Metadata-Version: 2.1
Name: estrutura-de-dados
Version: 0.0.1
Summary: Estrutura de Dados
Home-page: https://github.com/dev-rafa1707/estrutura_de_dados
Author: dev-rafa1707
Author-email: rafa1707@gmail.com
Requires-Python: >=3.8
